execution_controller/__init__.py
execution_controller/processes.py
execution_controller-0.1.7.dist-info/LICENSE
execution_controller-0.1.7.dist-info/WHEEL
execution_controller-0.1.7.dist-info/METADATA
execution_controller-0.1.7.dist-info/RECORD
